setup.py
sarf_listener/__init__.py
sarf_listener/bootstrap.py
sarf_listener/containers.py
sarf_listener.egg-info/PKG-INFO
sarf_listener.egg-info/SOURCES.txt
sarf_listener.egg-info/dependency_links.txt
sarf_listener.egg-info/requires.txt
sarf_listener.egg-info/top_level.txt