Metadata-Version: 2.1
Name: sarf-listener
Version: 1.0.0
Summary: Dependency required by sarf listeners
Home-page: https://github.com/elchicodepython/SARF-Security-Assesment-and-Reporting-Framework
Author: Samuel López Saura
Author-email: samuellopezsaura@gmail.com
License: MIT
Platform: UNKNOWN
Classifier: Programming Language :: Python :: 3
Classifier: License :: OSI Approved :: MIT License
Classifier: Operating System :: OS Independent
